flowable/__init__.py
flowable/rpaframework_client/API.py
flowable/rpaframework_client/__init__.py
flowable/rpaframework_client/__main__.py
flowable/rpaframework_client/call_python_module.py
flowable/rpaframework_client/rpaframework_handler.py
flowable.rpaframework_client-1.0.2.dist-info/METADATA
flowable.rpaframework_client-1.0.2.dist-info/WHEEL
flowable.rpaframework_client-1.0.2.dist-info/top_level.txt
flowable.rpaframework_client-1.0.2.dist-info/RECORD
