Metadata-Version: 2.1
Name: flowable.rpaframework-client
Version: 1.0.2
Summary: Flowable client to be used with rpaframework. This client connects to a Flowable instance via external worker and executes rpaframework robots or robocorp tasks or actions.
Author: Flowable
License: Apache License, Version 2.0
Requires-Dist: flowable.external-worker-client>=1.0.2
Provides-Extra: testing
Requires-Dist: pytest; extra == "testing"
Requires-Dist: vcrpy; extra == "testing"
Requires-Dist: flowable.external-worker-client>=1.0.2; extra == "testing"
Requires-Dist: robocorp-actions>=0.2.1; extra == "testing"
Requires-Dist: robocorp-tasks>=3.1.1; extra == "testing"
Requires-Dist: robocorp-truststore>=0.9.1; extra == "testing"
Requires-Dist: rpaframework; extra == "testing"
